chronomancer/__init__.py
chronomancer/cron/__init__.py
chronomancer/launchd/__init__.py
chronomancer/native/__init__.py
chronomancer/sched.py
chronomancer/systemd/__init__.py
chronomancer-0.1.0.dist-info/METADATA
chronomancer-0.1.0.dist-info/WHEEL
chronomancer-0.1.0.dist-info/RECORD
