Metadata-Version: 2.1
Name: chronomancer
Version: 0.1.0
Summary: 
License: MIT
Author: Nathan Lee
Author-email: lee.nathan.sh@outlook.com
Requires-Python: >=3.8.1,<4.0.0
Classifier: License :: OSI Approved :: MIT License
Classifier: Programming Language :: Python :: 3
Classifier: Programming Language :: Python :: 3.9
Classifier: Programming Language :: Python :: 3.10
Classifier: Programming Language :: Python :: 3.11
Classifier: Programming Language :: Python :: 3.12
Requires-Dist: fire (>=0.6.0,<0.7.0)
Requires-Dist: pydantic (>=2.6.4,<3.0.0)
Requires-Dist: schedule (>=1.2.1,<2.0.0)
Requires-Dist: tomli (>=2.0.1,<3.0.0)
